<requests>
    <header>
        <appName>pessoa</appName>
        <appPath>/db/apps/pessoa</appPath>
        <folders>
            <data>data</data>
            <statistics>magic</statistics>
        </folders>
    </header>
    <request id="1">
        <meta>
            <chartName>Genres</chartName>
            <chartType>pie</chartType>
            <subFolder>doc</subFolder>
        </meta>
        <style>
            <height>300</height>
            <width>600</width>
            <visibleWindow>
                <x1>-30</x1>
                <y1>30</y1>
                <x2>300</x2>
                <y2>1</y2>
            </visibleWindow>
            <color>custom</color>
        </style>
        <search>
            <type>range</type>
            <term>genre</term>
        </search>
        <fields>
            <field>
                <name>lista_editorial</name>
                <text>Lista Editorial</text>
                <color>#1DE813</color>
            </field>
            <field>
                <name>nota_editorial</name>
                <text>Nota Editorial</text>
                <color>#1B15FF</color>
            </field>
            <field>
                <name>plano_editorial</name>
                <text>Plano Editorial</text>
                <color>#E83E2E</color>
            </field>
        </fields>
    </request>
    <request id="2">
        <meta>
            <chartName>Roles</chartName>
            <chartType>bar</chartType>
            <subFolder>doc</subFolder>
        </meta>
        <style>
            <height>600</height>
            <width>300</width>
            <visibleWindow>
                <x1>-30</x1>
                <y1>-100</y1>
                <x2>300</x2>
                <y2>40</y2>
            </visibleWindow>
            <color>custom</color>
        </style>
        <search>
            <type>range</type>
            <term>role</term>
        </search>
        <fields>
            <field>
                <name>author</name>
                <text>Author</text>
                <color>#184BFF</color>
            </field>
            <field>
                <name>editor</name>
                <text>Editor</text>
                <color>#FF7120</color>
            </field>
            <field>
                <name>topic</name>
                <text>Topic</text>
                <color>#FF692A</color>
            </field>
            <field>
                <name>translator</name>
                <text>Translator</text>
                <color>#FF0813</color>
            </field>
        </fields>
    </request>
</requests>